larq_compute_engine-0.16.0.dist-info/RECORD
larq_compute_engine-0.16.0.dist-info/LICENSE
larq_compute_engine-0.16.0.dist-info/WHEEL
larq_compute_engine-0.16.0.dist-info/top_level.txt
larq_compute_engine-0.16.0.dist-info/METADATA
larq_compute_engine/__init__.py
larq_compute_engine/tflite/__init__.py
larq_compute_engine/tflite/python/interpreter_base.py
larq_compute_engine/tflite/python/__init__.py
larq_compute_engine/tflite/python/interpreter_wrapper_lite.so
larq_compute_engine/tflite/python/interpreter.py
larq_compute_engine/mlir/__init__.py
larq_compute_engine/mlir/_tf_tfl_flatbuffer.so
larq_compute_engine/mlir/python/util.py
larq_compute_engine/mlir/python/converter.py
larq_compute_engine/mlir/python/__init__.py
larq_compute_engine/mlir/python/tflite_schema.py
