Metadata-Version: 2.1
Name: larq-compute-engine
Version: 0.16.0
Summary: Highly optimized inference engine for binarized neural networks.
Home-page: https://larq.dev/
Author: Plumerai
Author-email: opensource@plumerai.com
License: Apache 2.0
Keywords: binarized neural networks
Classifier: Development Status :: 4 - Beta
Classifier: Intended Audience :: Developers
Classifier: Intended Audience :: Education
Classifier: Intended Audience :: Science/Research
Classifier: License :: OSI Approved :: Apache Software License
Classifier: Programming Language :: Python :: 3
Classifier: Programming Language :: Python :: 3 :: Only
Classifier: Programming Language :: Python :: 3.10
Classifier: Programming Language :: Python :: 3.11
Classifier: Programming Language :: Python :: 3.12
Classifier: Topic :: Scientific/Engineering
Classifier: Topic :: Scientific/Engineering :: Mathematics
Classifier: Topic :: Scientific/Engineering :: Artificial Intelligence
Classifier: Topic :: Software Development
Classifier: Topic :: Software Development :: Libraries
Classifier: Topic :: Software Development :: Libraries :: Python Modules
Requires-Python: >=3.10
License-File: LICENSE
Requires-Dist: flatbuffers >=2.0
Requires-Dist: tqdm >=4
Provides-Extra: tensorflow
Requires-Dist: tensorflow >=2.8 ; extra == 'tensorflow'
Provides-Extra: tensorflow_gpu
Requires-Dist: tensorflow-gpu >=2.8 ; extra == 'tensorflow_gpu'
